pyamlqt/__init__.py
pyamlqt/create_widgets.py
pyamlqt/label_configure.py
pyamlqt/load_yaml.py
pyamlqt/mainwindow.py
pyamlqt/qt6_switch.py
PyamlQt-0.3.1.dist-info/LICENSE
PyamlQt-0.3.1.dist-info/METADATA
PyamlQt-0.3.1.dist-info/WHEEL
PyamlQt-0.3.1.dist-info/entry_points.txt
PyamlQt-0.3.1.dist-info/top_level.txt
PyamlQt-0.3.1.dist-info/RECORD
