Metadata-Version: 2.1
Name: PyamlQt
Version: 0.3.1
Summary: PyQt6 configuration in yaml format providing the most simple script.
Home-page: https://github.com/Ar-Ray-code/PyamlQt
Author: Ar-Ray-code
Author-email: ray255ar@gmail.com
License: GPLv3
Project-URL: Source, https://github.com/Ar-Ray-code/PyamlQt
Project-URL: Tracker, https://github.com/Ar-Ray-code/PyamlQt/issues
Keywords: PyQt yaml
Platform: UNKNOWN
Classifier: License :: OSI Approved :: GNU General Public License v3 (GPLv3)
Classifier: Programming Language :: Python :: 3.8
Classifier: Programming Language :: Python :: 3.9
Requires-Python: >=3.8
Requires-Dist: PyQt6
Requires-Dist: PyYAML
